sendmail_docx/__init__.py
sendmail_docx/email_sender.py
tests/__init__.py
tests/test_email_sender_01.py
sendmail_docx-0.1.4.dist-info/LICENSE
sendmail_docx-0.1.4.dist-info/METADATA
sendmail_docx-0.1.4.dist-info/WHEEL
sendmail_docx-0.1.4.dist-info/top_level.txt
sendmail_docx-0.1.4.dist-info/RECORD
