Metadata-Version: 2.2
Name: sendmail-docx
Version: 0.1.4
Summary: Permite enviar correos electrónicos con plantillas DOCX.
Home-page: https://github.com/jmsanchez-ibiza/sendmail-docx
Author: José María Sánchez González
Author-email: jmsanchez.ibiza@gmail.com
License: MIT
Classifier: Programming Language :: Python :: 3
Classifier: License :: OSI Approved :: MIT License
Classifier: Operating System :: OS Independent
Requires-Python: >=3.7
License-File: LICENSE
Requires-Dist: python-docx
Requires-Dist: python-dotenv
Requires-Dist: mammoth
Dynamic: author
Dynamic: author-email
Dynamic: classifier
Dynamic: description
Dynamic: description-content-type
Dynamic: home-page
Dynamic: license
Dynamic: requires-dist
Dynamic: requires-python
Dynamic: summary
